findersel/__init__.py
findersel/core.py
findersel/settings.py
findersel/scripts/findersel.applescript
findersel-0.1.4.dist-info/LICENSE
findersel-0.1.4.dist-info/METADATA
findersel-0.1.4.dist-info/WHEEL
findersel-0.1.4.dist-info/top_level.txt
findersel-0.1.4.dist-info/RECORD
