Metadata-Version: 2.1
Name: findersel
Version: 0.1.4
Summary: Get selected files from macOS Finder.
Download-URL: https://github.com/sdelquin/findersel
Author: Sergio Delgado Quintero
Author-email: sdelquin@gmail.com
License: MIT
Project-URL: Issue Tracker, https://github.com/sdelquin/findersel/issues
Project-URL: Documentation, https://github.com/sdelquin/findersel/blob/main/README.md
Project-URL: Source Code, https://github.com/sdelquin/findersel
Keywords: macos finder files sysadmin selection
Platform: any
Classifier: Development Status :: 4 - Beta
Classifier: Intended Audience :: Developers
Classifier: License :: OSI Approved :: MIT License
Classifier: Operating System :: MacOS
Classifier: Programming Language :: Python
Classifier: Programming Language :: Python :: 3
Classifier: Programming Language :: Python :: 3 :: Only
Classifier: Programming Language :: Python :: 3.6
Classifier: Programming Language :: Python :: 3.7
Classifier: Programming Language :: Python :: 3.8
Classifier: Programming Language :: Python :: 3.9
Classifier: Programming Language :: Python :: 3.10
Classifier: Programming Language :: Python :: 3.11
Classifier: Topic :: Desktop Environment
Classifier: Topic :: System :: Filesystems
Classifier: Topic :: System :: Operating System
Classifier: Topic :: Utilities
Requires-Python: >=3.6
License-File: LICENSE
